koerce-0.5.1.dist-info/METADATA
koerce-0.5.1.dist-info/RECORD
koerce-0.5.1.dist-info/WHEEL
koerce-0.5.1.dist-info/LICENSE.txt
koerce/patterns.py
koerce/builders.py
koerce/_internal.py
koerce/__init__.py
koerce/utils.py
koerce/_internal.cpython-312-i386-linux-musl.so
koerce/annots.py
koerce/tests/test_utils.py
koerce/tests/test_sugar.py
koerce/tests/test_annots.py
koerce/tests/test_builders.py
koerce/tests/test_patterns.py
koerce/tests/__init__.py
koerce/tests/test_y.py
