Metadata-Version: 2.1
Name: koerce
Version: 0.5.1
Summary: Python Pattern Matching
License: Apache-2.0
Author: Krisztian Szucs
Author-email: szucs.krisztian@gmail.com
Requires-Python: >=3.8
Classifier: License :: OSI Approved :: Apache Software License
Classifier: Programming Language :: Python :: 3
Classifier: Programming Language :: Python :: 3.8
Classifier: Programming Language :: Python :: 3.9
Classifier: Programming Language :: Python :: 3.10
Classifier: Programming Language :: Python :: 3.11
Classifier: Programming Language :: Python :: 3.12
Requires-Dist: typing-extensions (>=4.12.2,<5.0.0)
